wnget/__init__.py
wnget/container.py
wnget/crawl.py
wnget/epub.py
wnget/main.py
wnget/utils.py
wnget/data/nav.css
wnget/data/sites.yaml
wnget-0.3.1.dist-info/DESCRIPTION.rst
wnget-0.3.1.dist-info/entry_points.txt
wnget-0.3.1.dist-info/METADATA
wnget-0.3.1.dist-info/metadata.json
wnget-0.3.1.dist-info/RECORD
wnget-0.3.1.dist-info/top_level.txt
wnget-0.3.1.dist-info/WHEEL
