Metadata-Version: 2.0
Name: wnget
Version: 0.3.1
Summary: web novel getter, a web scraping and ebook generation tool.
Home-page: https://github.com/unixwars/wnget
Author: Taher Shihadeh
Author-email: taher@unixwars.com
License: MIT
Keywords: webscraper epub ebook webnovel
Platform: UNKNOWN
Classifier: Development Status :: 4 - Beta
Classifier: Environment :: Console
Classifier: Topic :: Documentation
Classifier: Topic :: Utilities
Classifier: License :: OSI Approved :: MIT License
Classifier: Programming Language :: Python :: 2.7
Classifier: Programming Language :: Python :: 3.5
Requires-Dist: requests (>=2.9)
Requires-Dist: lxml (>=3.5)
Requires-Dist: eventlet (>=0.18)
Requires-Dist: ebooklib (>=0.15)
Requires-Dist: configargparse (>=0.10)
Requires-Dist: pyyaml (>=3)
